pandora/__init__.py
pandora/_utils.py
pandora/a2dp_grpc.py
pandora/a2dp_grpc_aio.py
pandora/a2dp_pb2.py
pandora/a2dp_pb2.pyi
pandora/host_grpc.py
pandora/host_grpc_aio.py
pandora/host_pb2.py
pandora/host_pb2.pyi
pandora/l2cap_grpc.py
pandora/l2cap_grpc_aio.py
pandora/l2cap_pb2.py
pandora/l2cap_pb2.pyi
pandora/py.typed
pandora/security_grpc.py
pandora/security_grpc_aio.py
pandora/security_pb2.py
pandora/security_pb2.pyi
bt_test_interfaces-0.0.6.dist-info/WHEEL
bt_test_interfaces-0.0.6.dist-info/METADATA
bt_test_interfaces-0.0.6.dist-info/RECORD
