Metadata-Version: 2.1
Name: bt-test-interfaces
Version: 0.0.6
Summary: Pandora gRPC Bluetooth test interfaces.
Author-email: Pandora <pandora-core@google.com>
Classifier: License :: OSI Approved :: Apache Software License
Requires-Dist: grpcio>=1.62.1
Requires-Dist: protobuf>=4.22.0
Requires-Dist: pyright==1.1.298 ; extra == "dev"
Requires-Dist: types-psutil==5.9.5.16 ; extra == "dev"
Requires-Dist: types-setuptools==68.1.0.1 ; extra == "dev"
Requires-Dist: types-protobuf==4.24.0.1 ; extra == "dev"
Project-URL: Source, https://github.com/google/bt-test-interfaces
Provides-Extra: dev
